LinghundeChushengqianJihua/Dockerfile
LinghundeChushengqianJihua/README.md
LinghundeChushengqianJihua/__init__.py
LinghundeChushengqianJihua/__main__.py
LinghundeChushengqianJihua/file.epub
LinghundeChushengqianJihua/index.html
LinghundeChushengqianJihua/css/__init__.py
LinghundeChushengqianJihua/css/annotations.css
LinghundeChushengqianJihua/css/main.css
LinghundeChushengqianJihua/css/normalize.css
LinghundeChushengqianJihua/css/popup.css
LinghundeChushengqianJihua/font/__init__.py
LinghundeChushengqianJihua/font/fontello.eot
LinghundeChushengqianJihua/font/fontello.svg
LinghundeChushengqianJihua/font/fontello.ttf
LinghundeChushengqianJihua/font/fontello.woff
LinghundeChushengqianJihua/img/__init__.py
LinghundeChushengqianJihua/img/annotator-glyph-sprite.png
LinghundeChushengqianJihua/img/annotator-icon-sprite.png
LinghundeChushengqianJihua/img/apple-touch-icon.png
LinghundeChushengqianJihua/img/cancelfullscreen.png
LinghundeChushengqianJihua/img/close.png
LinghundeChushengqianJihua/img/fullscreen.png
LinghundeChushengqianJihua/img/loader.gif
LinghundeChushengqianJihua/img/menu-icon.png
LinghundeChushengqianJihua/img/save.png
LinghundeChushengqianJihua/img/saved.png
LinghundeChushengqianJihua/img/settings-s.png
LinghundeChushengqianJihua/img/settings.png
LinghundeChushengqianJihua/img/star.png
LinghundeChushengqianJihua/js/__init__.py
LinghundeChushengqianJihua/js/epub.js
LinghundeChushengqianJihua/js/epub.min.js
LinghundeChushengqianJihua/js/epub.min.map
LinghundeChushengqianJihua/js/hooks.min.js
LinghundeChushengqianJihua/js/hooks.min.map
LinghundeChushengqianJihua/js/reader.js
LinghundeChushengqianJihua/js/reader.js.map
LinghundeChushengqianJihua/js/reader.min.js
LinghundeChushengqianJihua/js/reader.min.map
LinghundeChushengqianJihua/js/hooks/__init__.py
LinghundeChushengqianJihua/js/hooks/extensions/__init__.py
LinghundeChushengqianJihua/js/hooks/extensions/highlight.js
LinghundeChushengqianJihua/js/libs/__init__.py
linghunde_chushengqian_jihua-2022.10.3.0.dist-info/METADATA
linghunde_chushengqian_jihua-2022.10.3.0.dist-info/WHEEL
linghunde_chushengqian_jihua-2022.10.3.0.dist-info/entry_points.txt
linghunde_chushengqian_jihua-2022.10.3.0.dist-info/top_level.txt
linghunde_chushengqian_jihua-2022.10.3.0.dist-info/RECORD
